ckanext/__init__.py
ckanext/thumbnailer/__init__.py
ckanext/thumbnailer/cli.py
ckanext/thumbnailer/config.py
ckanext/thumbnailer/config_declaration.yaml
ckanext/thumbnailer/helpers.py
ckanext/thumbnailer/plugin.py
ckanext/thumbnailer/utils.py
ckanext/thumbnailer/assets/script.js
ckanext/thumbnailer/assets/style.css
ckanext/thumbnailer/assets/webassets.yml
ckanext/thumbnailer/logic/__init__.py
ckanext/thumbnailer/logic/action.py
ckanext/thumbnailer/logic/auth.py
ckanext/thumbnailer/tests/__init__.py
ckanext/thumbnailer/tests/test_plugin.py
ckanext_thumbnailer-0.1.4.post1.dist-info/LICENSE
ckanext_thumbnailer-0.1.4.post1.dist-info/METADATA
ckanext_thumbnailer-0.1.4.post1.dist-info/WHEEL
ckanext_thumbnailer-0.1.4.post1.dist-info/entry_points.txt
ckanext_thumbnailer-0.1.4.post1.dist-info/top_level.txt
ckanext_thumbnailer-0.1.4.post1.dist-info/RECORD
