Metadata-Version: 2.1
Name: ckanext-thumbnailer
Version: 0.1.4.post1
Author-email: DataShades <datashades@linkdigital.com.au>, Sergey Motornyuk <sergey.motornyuk@linkdigital.com.au>
Maintainer-email: DataShades <datashades@linkdigital.com.au>
License: AGPL
Project-URL: Homepage, https://github.com/DataShades/ckanext-thumbnailer
Keywords: CKAN
Classifier: Development Status :: 4 - Beta
Classifier: License :: OSI Approved :: GNU Affero General Public License v3 or later (AGPLv3+)
Classifier: Programming Language :: Python :: 3.8
Classifier: Programming Language :: Python :: 3.9
Classifier: Programming Language :: Python :: 3.10
Classifier: Programming Language :: Python :: 3.11
Classifier: Programming Language :: Python :: 3.12
Classifier: Programming Language :: Python :: 3.13
Classifier: Programming Language :: Python :: 3.14
Requires-Python: >=3.8
License-File: LICENSE
Requires-Dist: typing-extensions
Requires-Dist: preview-generator
Requires-Dist: ckanext-toolbelt
Requires-Dist: ckanext-files <2.0,>=1.0.0a0
Provides-Extra: all
Requires-Dist: preview-generator[all] ; extra == 'all'
